{
  "categories": [
    {
      "id": "entrantes",
      "name": {
        "en": "Starters",
        "es": "Entrantes",
        "ca": "Entrants",
        "fr": "Entrées",
        "it": "Antipasti",
        "de": "Vorspeisen",
        "ru": "Закуски"
      },
      "slug": "entrantes",
      "description": {
        "en": "To whet your appetite. And spark conversation. The kind that lands in the middle of the table and vanishes before the drinks are ordered.",
        "es": "Para abrir boca. Y conversación.De los que llegan al centro de la mesa y desaparecen antes de pedir la bebida.",
        "ca": "Per obrir la gana. I la conversa. D’aquells que arriben al centre de la taula i desapareixen abans de demanar la beguda.",
        "fr": "Pour éveiller l’appétit. Et la conversation. De ceux qu’on pose au centre de la table et qui disparaissent avant même de commander à boire.",
        "it": "Per stuzzicare l’appetito. E la conversazione. Di quelli che arrivano al centro tavola e spariscono prima ancora di ordinare da bere.",
        "de": "Zum Appetit anregen. Und Gespräche entfachen. Die Art von Gerichten, die in der Mitte des Tisches landen und verschwunden sind, noch bevor die Getränke bestellt werden.",
        "ru": "Чтобы разыгрался аппетит. И завязался разговор. Те, что ставят в центр стола — и они исчезают, ещё до того как заказали напитки."
      }
    },
    {
      "id": "pastas",
      "name": {
        "en": "Pasta",
        "es": "Pastas",
        "ca": "Pastes",
        "fr": "Pâtes",
        "it": "Paste",
        "de": "Nudeln",
        "ru": "Паста"
      },
      "slug": "pastas",
      "description": {
        "en": "They’re not Italian. They’re ours. And no, you don’t have to share them.",
        "es": "No son italianas. Son nuestras. Y no, no hace falta compartirlas.",
        "ca": "No són italianes. Són nostres. I no, no cal compartir-les.",
        "fr": "Elles ne sont pas italiennes. Elles sont à nous. Et non, pas besoin de les partager.",
        "it": "Non sono italiane. Sono le nostre. E no, non serve condividerle.",
        "de": "Sie sind nicht italienisch. Sie sind unsere. Und nein, man muss sie nicht teilen.",
        "ru": "Они не итальянские. Они наши. И нет, делиться ими не обязательно."
      }
    },
    {
      "id": "pizzas",
      "name": {
        "en": "Pizzas",
        "es": "Pizzas",
        "ca": "Pizzes",
        "fr": "Pizzas",
        "it": "Pizze",
        "de": "Pizzas",
        "ru": "Пиццы"
      },
      "slug": "pizzas",
      "description": {
        "en": "Round, yes. But straight to the point",
        "es": "Redondas, sí. Pero sin rodeos",
        "ca": "Rodones, sí. Però sense embuts",
        "fr": "Rondes, oui. Mais sans détour",
        "it": "Tonde, sì. Ma senza giri di parole",
        "de": "Rund, ja. Aber ohne Umschweife",
        "ru": "Круглые да. Но без лишних слов"
      }
    },
    {
      "id": "carnes-pescados",
      "name": {
        "en": "Meat & Fish",
        "es": "Carnes y Pescados",
        "ca": "Carns i Peixos",
        "fr": "Viandes et Poissons",
        "it": "Carni e Pesci",
        "de": "Fleisch und Fisch",
        "ru": "Мясо и рыба"
      },
      "slug": "carnes-pescados",
      "description": {
        "en": "Dishes with character. The kind you order when you want to get it right",
        "es": "Platos con carácter. De los que pides cuando quieres acertar",
        "ca": "Plats amb caràcter. D’aquells que demanes quan vols encertar",
        "fr": "Des plats avec du caractère. Ceux qu’on commande quand on ne veut pas se tromper",
        "it": "Piatti con carattere. Di quelli che ordini quando vuoi andare sul sicuro",
        "de": "Gerichte mit Charakter. Die, die man bestellt, wenn man nichts falsch machen will",
        "ru": "Блюда с характером. Те самые, что заказываешь, когда хочешь не прогадать"
      }
    },
    {
      "id": "postres",
      "name": {
        "en": "Desserts",
        "es": "Postres",
        "ca": "Postres",
        "fr": "Desserts",
        "it": "Dolci",
        "de": "Desserts",
        "ru": "Десерты"
      },
      "slug": "postres",
      "description": {
        "en": "The happy ending isn’t optional",
        "es": "El final feliz no es opcional",
        "ca": "El final feliç no és opcional",
        "fr": "Le happy end n’est pas facultatif",
        "it": "Il lieto fine è d’obbligo",
        "de": "Ein Happy End ist Pflicht",
        "ru": "Счастливый финал не обсуждается."
      }
    }
  ],
  "items": [
    {
      "id": "croquetas-iberico",
      "name": {
        "en": "Pure Iberian ham croquettes",
        "es": "Croquetas de puro Ibérico",
        "ca": "Croquetes de pur Ibèric",
        "fr": "Croquettes au jambon ibérique pur",
        "it": "Crocchette di puro prosciutto iberico",
        "de": "Kroketten aus reinem iberischem Schinken",
        "ru": "Крокеты из чистой иберийской ветчины"
      },
      "description": {
        "en": "",
        "es": "",
        "ca": "",
        "fr": "",
        "it": "",
        "de": "",
        "ru": ""
      },
      "price": "9,00",
      "categoryId": "entrantes",
      "image": "/images/menu/croquetas.jpg"
    },
    {
      "id": "tartar-atun",
      "name": {
        "en": "Tuna tartare with avocado and Asian dressing",
        "es": "Tartar de atún, aguacate y aliño asiático",
        "ca": "Tàrtar de tonyina, alvocat i amaniment asiàtic",
        "fr": "Tartare de thon, avocat et vinaigrette asiatique",
        "it": "Tartare di tonno con avocado e condimento asiatico",
        "de": "Thunfisch-Tartar mit Avocado und asiatischem Dressing",
        "ru": "Тартар из тунца с авокадо и азиатской заправкой"
      },
      "description": {
        "en": "",
        "es": "",
        "ca": "",
        "fr": "",
        "it": "",
        "de": "",
        "ru": ""
      },
      "price": "17,00",
      "categoryId": "entrantes",
      "image": "/images/menu/tartar-atun.jpg"
    },
    {
      "id": "carpaccio-presa",
      "name": {
        "en": "Iberian pork shoulder carpaccio marinated in Izaguirre vermouth and chili peppers",
        "es": "Carpaccio de presa ibérica marinado en vermut Izaguirre y guindillas",
        "ca": "Carpaccio de presa ibèrica marinat en vermut Izaguirre i bitxo",
        "fr": "Carpaccio d'épaule de porc ibérique mariné au vermouth Izaguirre et piments",
        "it": "Carpaccio di maiale iberico marinato in vermouth Izaguirre e peperoncini",
        "de": "Carpaccio vom iberischen Schweineschulter, mariniert in Izaguirre-Wermut mit Chilischoten",
        "ru": "Карпаччо из иберийской свинины, маринованное в вермуте Изагирре, с фисташками и перцем чили"
      },
      "description": {
        "en": "",
        "es": "",
        "ca": "",
        "fr": "",
        "it": "",
        "de": "",
        "ru": ""
      },
      "price": "11,00",
      "categoryId": "entrantes",
      "image": "/images/menu/carpaccio.jpg"
    },
    {
      "id": "ensalada-berenjena",
      "name": {
        "en": "Roasted eggplant salad with goat cheese and avocado",
        "es": "Ensalada de berenjena asada, queso de cabra y aguacate",
        "ca": "Amanida d'albergínia rostida, formatge de cabra i alvocat",
        "fr": "Salade d'aubergine rôtie, fromage de chèvre et avocat",
        "it": "Insalata di melanzane arrostite, formaggio di capra e avocado",
        "de": "Salat aus gebratener Aubergine mit Ziegenkäse und Avocado",
        "ru": "Салат из запеченных баклажанов с козьим сыром и авокадо"
      },
      "description": {
        "en": "",
        "es": "",
        "ca": "",
        "fr": "",
        "it": "",
        "de": "",
        "ru": ""
      },
      "price": "12,00",
      "categoryId": "entrantes",
      "image": "/images/menu/ensalada-berenjena.jpg"
    },
    {
      "id": "aguacate-salmon",
      "name": {
        "en": "Emulsified avocado with salmon and sesame seeds",
        "es": "Aguacate emulsionado, salmón y sésamo",
        "ca": "Alvocat emulsionat, salmó i sèsam",
        "fr": "Avocat émulsionné, saumon et graines de sésame",
        "it": "Avocado emulsionato con salmone e semi di sesamo",
        "de": "Emulgierte Avocado mit Lachs und Sesamsamen",
        "ru": "Эмульгированный авокадо с лососем и семенами кунжута"
      },
      "description": {
        "en": "",
        "es": "",
        "ca": "",
        "fr": "",
        "it": "",
        "de": "",
        "ru": ""
      },
      "price": "7,50",
      "categoryId": "entrantes",
      "image": "/images/menu/aguacate-salmon.jpg"
    },
    {
      "id": "fritos-calaf",
      "name": {
        "en": "Calaf fritters with crystal shrimp and citrus",
        "es": "Los fritos de Calaf, gamba cristal y cítricos",
        "ca": "Els fregits de Calaf, gamba cristall i cítrics",
        "fr": "Frits de Calaf, crevette cristal et agrumes",
        "it": "Fritti di Calaf, gambero cristallo e agrumi",
        "de": "Calaf-Fritters mit Glasgarnelen und Zitrusfrüchten",
        "ru": "Жареные кусочки калаф с прозрачными креветками и цитрусовыми"
      },
      "description": {
        "en": "",
        "es": "",
        "ca": "",
        "fr": "",
        "it": "",
        "de": "",
        "ru": ""
      },
      "price": "11,00",
      "categoryId": "entrantes",
      "image": "/images/menu/fritos-calaf.jpg"
    },
    {
      "id": "ensalada-cesar",
      "name": {
        "en": "Our version of the classic Caesar salad",
        "es": "Nuestra versión de la ensalada César",
        "ca": "La nostra versió de l'amanida Cèsar",
        "fr": "Notre version de la salade César",
        "it": "La nostra versione dell'insalata Caesar",
        "de": "Unsere Version des Caesar-Salats",
        "ru": "Наша версия салата Цезарь"
      },
      "description": {
        "en": "",
        "es": "",
        "ca": "",
        "fr": "",
        "it": "",
        "de": "",
        "ru": ""
      },
      "price": "12,50",
      "categoryId": "entrantes",
      "image": "/images/menu/ensalada-cesar.jpg"
    },
    {
      "id": "raviolis-rabo",
      "name": {
        "en": "Oxtail ravioli cooked in a traditional way with pecorino cheese",
        "es": "Raviolis de rabo de toro guisado a la antigua y queso pecorino",
        "ca": "Raviolis de cua de bou guisat a l'antiga i formatge pecorino",
        "fr": "Raviolis de queue de bœuf cuisinée à l'ancienne et fromage pecorino",
        "it": "Ravioli di coda di bue stufata all'antica e formaggio pecorino",
        "de": "Ravioli mit traditionell geschmortem Ochsenschwanz und Pecorino-Käse",
        "ru": "Равиоли из бычьего хвоста, тушенного по-старинному, с сыром пекорино"
      },
      "description": {
        "en": "",
        "es": "",
        "ca": "",
        "fr": "",
        "it": "",
        "de": "",
        "ru": ""
      },
      "price": "17,50",
      "categoryId": "entrantes",
      "image": "/images/menu/raviolis.jpg"
    },
    {
      "id": "ensalada-tomate",
      "name": {
        "en": "Seasonal tomato salad with Kalamata olives and homemade confit tuna",
        "es": "Ensalada de tomates de temporada, aceitunas kalamata y ventresca de atún confitada",
        "ca": "Amanida de tomàquets de temporada, olives kalamata i ventresca de tonyina confitada",
        "fr": "Salade de tomates de saison, olives Kalamata et ventresque de thon confite maison",
        "it": "Insalata di pomodori di stagione con olive Kalamata e tonno confit fatto in casa",
        "de": "Saisonale Tomatensalat mit Kalamata-Oliven und hausgemachtem Thunfisch-Confit",
        "ru": "Салат из сезонных помидоров с оливками Каламата и домашним конфитюром из тунца"
      },
      "description": {
        "en": "",
        "es": "",
        "ca": "",
        "fr": "",
        "it": "",
        "de": "",
        "ru": ""
      },
      "price": "12,50",
      "categoryId": "entrantes",
      "image": "/images/menu/ensalada-tomate.jpg"
    },
    {
      "id": "mejillones",
      "name": {
        "en": "Mussels steamed with citrus and herbs",
        "es": "Mejillones al vapor de cítricos y hierbas",
        "ca": "Musclos al vapor de cítrics i herbes",
        "fr": "Moules à la vapeur d'agrumes et d'herbes",
        "it": "Cozze al vapore di agrumi ed erbe",
        "de": "Gedämpfte Muscheln mit Zitrusfrüchten und Kräutern",
        "ru": "Мидии на пару с цитрусовыми и травами"
      },
      "description": {
        "en": "",
        "es": "",
        "ca": "",
        "fr": "",
        "it": "",
        "de": "",
        "ru": ""
      },
      "price": "9,00",
      "categoryId": "entrantes",
      "image": "/images/menu/mejillones.jpg"
    },
    {
      "id": "hummus",
      "name": {
        "en": "Eggplant hummus served with raw vegetables",
        "es": "Hummus de berenjena y crudités",
        "ca": "Hummus d'albergínia i crudités",
        "fr": "Houmous d'aubergine servi avec des crudités",
        "it": "Hummus di melanzane servito con verdure crude",
        "de": "Auberginen-Hummus serviert mit rohem Gemüse",
        "ru": "Хумус из баклажанов, подаваемый с сырыми овощами"
      },
      "description": {
        "en": "",
        "es": "",
        "ca": "",
        "fr": "",
        "it": "",
        "de": "",
        "ru": ""
      },
      "price": "9,50",
      "categoryId": "entrantes",
      "image": "/images/menu/hummus.jpg"
    },
    {
      "id": "arrabiata",
      "name": {
        "en": "Arrabiata",
        "es": "Arrabiata",
        "ca": "Arrabiata",
        "fr": "Arrabiata",
        "it": "Arrabiata",
        "de": "Arrabiata",
        "ru": "Arrabiata"
      },
      "description": {
        "en": "Rigatoni with spicy sauce made with tomato, garlic, chili pepper and olive oil",
        "es": "Rigatoni con salsa picante a base de tomate, ajo, guindilla y aceite de oliva",
        "ca": "Rigatoni amb salsa picant a base de tomàquet, all, bitxo i oli d'oliva",
        "fr": "Rigatoni avec sauce épicée à base de tomate, ail, piment et huile d'olive",
        "it": "Rigatoni con salsa piccante a base di pomodoro, aglio, peperoncino e olio d'oliva",
        "de": "Rigatoni mit scharfer Sauce aus Tomaten, Knoblauch, Chili und Olivenöl",
        "ru": "Ригатони с острым соусом на основе томатов, чеснока, перца чили и оливкового масла"	
      },
      "price": "12,00",
      "categoryId": "pastas",
      "image": "/images/menu/arrabiata.jpg"
    },
    {
      "id": "carbonara",
      "name": {
        "en": "Alla Carbonara",
        "es": "Alla Carbonara",
        "ca": "Alla Carbonara",
        "fr": "Alla Carbonara",
        "it": "Alla Carbonara",
        "de": "Alla Carbonara",
        "ru": "Alla Carbonara"
      },
      "description": {
        "en": "Tagliatelle with carbonara sauce made with guanciale and parmesan",
        "es": "Tagliatelle con salsa carbonara de guanchale y parmesano",
        "ca": "Tagliatelle amb salsa carbonara de guanciale i parmesà",
        "fr": "Tagliatelle avec sauce carbonara au guanciale et parmesan",
        "it": "Tagliatelle con salsa carbonara di guanciale e parmigiano",
        "de": "Tagliatelle mit Carbonara-Sauce aus Guanciale und Parmesan",
        "ru": "Ригатони с соусом карбонара из гуанчале и пармезана"
      },
      "price": "14,00",
      "categoryId": "pastas",
      "image": "/images/menu/carbonara.jpg"
    },
    {
      "id": "bolognesa",
      "name": {
        "en": "Alla Bolognesa",
        "es": "Alla Bolognesa",
        "ca": "Alla Bolognesa",
        "fr": "Alla Bolognesa",
        "it": "Alla Bolognesa",
        "de": "Alla Bolognesa",
        "ru": "Alla Bolognesa"
      },
      "description": {
        "en": "Spaghetti with Bolognese sauce, organic tomato and fresh basil",
        "es": "Spaghetti con salsa boloñesa, tomate ecológico y albahaca fresca",
        "ca": "Spaghetti amb salsa bolonyesa, tomàquet ecològic i alfàbrega fresca",
        "fr": "Spaghetti avec sauce bolognaise, tomate bio et basilic frais",
        "it": "Spaghetti con ragù alla bolognese, pomodoro biologico e basilico fresco",
        "de": "Spaghetti mit Bolognese-Sauce, Bio-Tomaten und frischem Basilikum",
        "ru": "Спагетти с соусом болоньезе, органическими томатами и свежим базиликом"
      },
      "price": "9,00",
      "categoryId": "pastas",
      "image": "/images/menu/bolognesa.jpg"
    },
    {
      "id": "pizza-picante",
      "name": {
        "en": "Spicy",
        "es": "Picante",
        "ca": "Picant",
        "fr": "Picante",
        "it": "Picante",
        "de": "Picante",
        "ru": "Picante"
      },
      "description": {
        "en": "Organic tomato, spicy pepperoni and black olives",
        "es": "Tomate ecológico, pepperoni picante y aceitunas negras",
        "ca": "Tomàquet ecològic, pepperoni picant i olives negres",
        "fr": "Tomate bio, pepperoni épicé et olives noires",
        "it": "Pomodoro biologico, pepperoni piccante e olive nere",
        "de": "Bio-Tomaten, scharfe Pepperoni und schwarze Oliven",
        "ru": "Органические помидоры, острая пепперони и черные оливки"
      },
      "price": "14,50",
      "categoryId": "pizzas",
      "image": "/images/menu/pizza-picante.jpg"
    },
    {
      "id": "pizza-formaggi",
      "name": {
        "en": "Formaggi",
        "es": "Formaggi",
        "ca": "Formaggi",
        "fr": "Formaggi",
        "it": "Formaggi",
        "de": "Formaggi",
        "ru": "Formaggi"
      },
      "description": {
        "en": "A selection of four melted cheeses, tomato and mozzarella",
        "es": "Selección de cuatro quesos fundidos, tomate y mozzarella",
        "ca": "Selecció de quatre formatges fosos, tomàquet i mozzarella",
        "fr": "Sélection de quatre fromages fondus, tomate et mozzarella",
        "it": "Selezione di quattro formaggi fusi, pomodoro e mozzarella",
        "de": "Auswahl von vier geschmolzenen Käsesorten, Tomaten und Mozzarella",
        "ru": "Выбор из четырех плавленых сыров, помидоров и моцареллы"
      },
      "price": "15,50",
      "categoryId": "pizzas",
      "image": "/images/menu/pizza-formaggi.jpg"
    },
    {
      "id": "pizza-napolitana",
      "name": {
        "en": "Napolitana",
        "es": "Napolitana",
        "ca": "Napolitana",
        "fr": "Napolitana",
        "it": "Napolitana",
        "de": "Napolitana",
        "ru": "Napolitana"
      },
      "description": {
        "en": "Bresaola, anchovy and fresh arugula",
        "es": "Bresaola, anchoa y rúcula fresca",
        "ca": "Bresaola, anxova i ruca fresca",
        "fr": "Bresaola, anchois et roquette fraîche",
        "it": "Bresaola, acciuga e rucola fresca",
        "de": "Bresaola, Sardelle und frischer Rucola",
        "ru": "Брезаола, анчоусы и свежий руккола"
      },
      "price": "14,20",
      "categoryId": "pizzas",
      "image": "/images/menu/pizza-napolitana.jpg"
    },
    {
      "id": "pizza-bbq",
      "name": {
        "en": "NY BBQ",
        "es": "NY BBQ",
        "ca": "NY BBQ",
        "fr": "NY BBQ",
        "it": "NY BBQ",
        "de": "NY BBQ",
        "ru": "NY BBQ"
      },
      "description": {
        "en": "Slow-cooked chicken, homemade barbecue sauce and mozzarella",
        "es": "Pollo a baja temperatura, salsa barbacoa casera y mozzarella",
        "ca": "Pollastre a baixa temperatura, salsa barbacoa casolana i mozzarella",
        "fr": "Poulet à basse température, sauce barbecue maison et mozzarella",
        "it": "Pollo a bassa temperatura, salsa barbecue fatta in casa e mozzarella",
        "de": "Hähnchen bei niedriger Temperatur, hausgemachte Barbecue-Sauce und Mozzarella",
        "ru": "Курица, приготовленная при низкой температуре, домашний соус барбекю и моцарелла"
      },
      "price": "15,20",
      "categoryId": "pizzas",
      "image": "/images/menu/pizza-bbq.jpg"
    },
    {
      "id": "pizza-margherita",
      "name": {
        "en": "margherita",
        "es": "margherita",
        "ca": "margherita",
        "fr": "margherita",
        "it": "margherita",
        "de": "margherita",
        "ru": "margherita"
      },
      "description": {
        "en": "Homemade tomato sauce, buffalo mozzarella, basil and garlic oil",
        "es": "Salsa tomate casera, mozzarella de búfala y albahaca y aceite de ajos",
        "ca": "Salsa de tomàquet casolana, mozzarella de búfala, alfàbrega i oli d'all",
        "fr": "Sauce tomate maison, mozzarella de bufala, basilic et huile d'ail",
        "it": "Salsa di pomodoro fatta in casa, mozzarella di bufala, basilico e olio all'aglio",
        "de": "Hausgemachte Tomatensauce, Büffelmozzarella, Basilikum und Knoblauchöl",
        "ru": "Домашний томатный соус, моцарелла из буйволиного молока, базилик и чесночное масло"
      },
      "price": "14,00",
      "categoryId": "pizzas",
      "image": "/images/menu/pizza-margherita.jpg"
    },
    {
      "id": "pizza-carbonara",
      "name": {
        "en": "Carbonara",
        "es": "Carbonara",
        "ca": "Carbonara",
        "fr": "Carbonara",
        "it": "Carbonara",
        "de": "Carbonara",
        "ru": "Carbonara"
      },
      "description": {
        "en": "Carbonara sauce with low-temperature cooked egg",
        "es": "Salsa carbonara con huevo cocinado a baja temperatura",
        "ca": "Salsa carbonara amb ou cuit a baixa temperatura",
        "fr": "Sauce carbonara avec œuf cuit à basse température",
        "it": "Salsa carbonara con uovo cotto a bassa temperatura",
        "de": "Carbonara-Sauce mit Ei, das bei niedriger Temperatur gekocht wurde",
        "ru": "Соус карбонара с яйцом, приготовленным при низкой температуре"
      },
      "price": "15,20",
      "categoryId": "pizzas",
      "image": "/images/menu/pizza-carbonara.jpg"
    },
    {
      "id": "pizza-escalivada",
      "name": {
        "en": "Escalivada",
        "es": "Escalivada",
        "ca": "Escalivada",
        "fr": "Escalivada",
        "it": "Escalivada",
        "de": "Escalivada",
        "ru": "Escalivada"
      },
      "description": {
        "en": "Catalan-style Roasted vegetables with pistachio pesto",
        "es": "Escalivada con pesto de pistachos",
        "ca": "Escalivada amb pesto de pinyons",
        "fr": "Légumes rôtis à la catalane avec pesto de pistaches",
        "it": "Escalivada con pesto di pistacchi",
        "de": "Escalivada mit Pistazienpesto",
        "ru": "Эскаливада с песто из фисташек"
      },
      "price": "15,50",
      "categoryId": "pizzas",
      "image": "/images/menu/pizza-escalivada.jpg"
    },
    {
      "id": "lomo-bajo",
      "name": {
        "en": "Girona beef loin with creamy celeriac and its jus",
        "es": "Lomo bajo de ternera de Girona, cremoso de apionabo y su jugo",
        "ca": "Llom baix de vedella de Girona, cremós d'api-rave i el seu suc",
        "fr": "Longe de bœuf de Girona, crémeux de céleri-rave et son jus",
        "it": "Lombata di manzo di Girona, cremoso di sedano rapa e il suo sugo",
        "de": "Rinderlende aus Girona mit cremiger Sellerieknolle und ihrem Saft",
        "ru": "Говяжья вырезка из Жироны с кремовым сельдереем и соком"
      },
      "description": {
        "en": "",
        "es": "",
        "ca": "",
        "fr": "",
        "it": "",
        "de": "",
        "ru": ""
      },
      "price": "19,50",
      "categoryId": "carnes-pescados",
      "image": "/images/menu/lomo-bajo.jpg"
    },
    {
      "id": "pollo-picanton",
      "name": {
        "en": "Young chicken in its own juice, accompanied by mini carrots marinated with citrus",
        "es": "Pollo picantón en su jugo, acompañado de mini zanahorias escabechadas con cítricos",
        "ca": "Pollastró en el seu suc, acompanyat de mini pastanagues escabetxades amb cítrics",
        "fr": "Jeune poulet dans son jus, accompagné de mini carottes marinées aux agrumes",
        "it": "Pollo piccante nel suo sugo, accompagnato da mini carote marinate agli agrumi",
        "de": "Junges Hähnchen in seinem Saft, begleitet von Mini-Karotten mariniert mit Zitrusfrüchten",
        "ru": "Молодой цыпленок в собственном соку с мини-морковью, маринованной с цитрусовыми"
      },
      "description": {
        "en": "",
        "es": "",
        "ca": "",
        "fr": "",
        "it": "",
        "de": "",
        "ru": ""
      },
      "price": "16,40",
      "categoryId": "carnes-pescados",
      "image": "/images/menu/pollo-picanton.jpg"
    },
    {
      "id": "cordero",
      "name": {
        "en": "Lamb shoulder with lettuce heart salad, spring onions, and wood-fired roasted peppers",
        "es": "Paletilla de cordero, ensalada de cogollos y cebolletas, y pimientos asados a la leña",
        "ca": "Espatlla de xai, amanida de cabdells i cebes tendres, i pebrots rostits a la llenya",
        "fr": "Épaule d'agneau, salade de cœurs de laitue et oignons nouveaux, et poivrons rôtis au feu de bois",
        "it": "Spalla d'agnello, insalata di cuori di lattuga e cipollotti, e peperoni arrostiti al legno",
        "de": "Lammschulter mit Salatherzen, Frühlingszwiebeln und am Holzfeuer gerösteten Paprika",
        "ru": "Лопатка ягненка с салатом из кочанного салата, зеленого лука и перцев, жаренных на дровах"
      },
      "description": {
        "en": "",
        "es": "",
        "ca": "",
        "fr": "",
        "it": "",
        "de": "",
        "ru": ""
      },
      "price": "24,50",
      "categoryId": "carnes-pescados",
      "image": "/images/menu/cordero.jpg"
    },
    {
      "id": "solomillo",
      "name": {
        "en": "Beef fillet with mashed potato and jus",
        "es": "Solomillo acompañado de patata enmascarada y su jugo",
        "ca": "Filet acompanyat de patata emmascarada i el seu suc",
        "fr": "Filet de bœuf, purée de pomme de terre au boudin noir et son jus",
        "it": "Filetto di manzo accompagnato da patata mascherata e il suo sugo",
        "de": "Rinderfilet mit maskierter Kartoffel und seinem Saft",
        "ru": "Говяжья вырезка с картофельным пюре и соком"
      },
      "description": {
        "en": "",
        "es": "",
        "ca": "",
        "fr": "",
        "it": "",
        "de": "",
        "ru": ""
      },
      "price": "29,00",
      "categoryId": "carnes-pescados",
      "image": "/images/menu/solomillo.jpg"
    },
    {
      "id": "salmon",
      "name": {
        "en": "Salmon with spiced butter and seasonal vegetables",
        "es": "Salmón a la mantequilla de especias y verduritas de temporada",
        "ca": "Salmó a la mantega d'espècies i verduretes de temporada",
        "fr": "Saumon au beurre aux épices et petits légumes de saison",
        "it": "Salmone al burro alle spezie e verdure di stagione",
        "de": "Lachs mit Gewürzbutter und Saisongemüse",
        "ru": "Лосось со сливочным маслом со специями и сезонными овощами"
      },
      "description": {
        "en": "",
        "es": "",
        "ca": "",
        "fr": "",
        "it": "",
        "de": "",
        "ru": ""
      },
      "price": "18,00",
      "categoryId": "carnes-pescados",
      "image": "/images/menu/salmon.jpg"
    },
    {
      "id": "merluza",
      "name": {
        "en": "Hake Donostiarra style with Mahón cheese parmentier",
        "es": "Merluza a la donostiarra y parmentier de queso Mahón",
        "ca": "Lluç a la donostiarra i parmentier de formatge Maó",
        "fr": "Merlu à la Donostiarra et parmentier de fromage Mahón",
        "it": "Nasello alla Donostiarra e parmentier di formaggio Mahón",
        "de": "Seehecht nach Donostiarra-Art mit Mahón-Käse-Parmentier",
        "ru": "Хек по-доностьярски с пармантье из сыра Маон"
      },
      "description": {
        "en": "",
        "es": "",
        "ca": "",
        "fr": "",
        "it": "",
        "de": "",
        "ru": ""
      },
      "price": "18,00",
      "categoryId": "carnes-pescados",
      "image": "/images/menu/merluza.jpg"
    },
    {
      "id": "tiramisu",
      "name": {
        "en": "Matcha Tea Tiramisu",
        "es": "Tiramisú de té matcha",
        "ca": "Tiramisú de te matcha",
        "fr": "Tiramisu au thé matcha",
        "it": "Tiramisù al tè matcha",
        "de": "Matcha-Tee-Tiramisu",
        "ru": "Тирамису с чаем матча"
      },
      "description": {
        "en": "",
        "es": "",
        "ca": "",
        "fr": "",
        "it": "",
        "de": "",
        "ru": ""
      },
      "price": "7,00",
      "categoryId": "postres",
      "image": "/images/menu/tiramisu.jpg"
    },
    {
      "id": "flan",
      "name": {
        "en": "Creamy mascarpone cheese flan",
        "es": "Flan cremoso de mascarpone",
        "ca": "Flam cremós de mascarpone",
        "fr": "Flan crémeux au mascarpone",
        "it": "Flan cremoso al mascarpone",
        "de": "Cremiger Pudding aus Mascarpone",
        "ru": "Кремовый флан из сыра маскарпоне"
      },
      "description": {
        "en": "",
        "es": "",
        "ca": "",
        "fr": "",
        "it": "",
        "de": "",
        "ru": ""
      },
      "price": "7,00",
      "categoryId": "postres",
      "image": "/images/menu/flan.jpg"
    },
    {
      "id": "frutas",
      "name": {
        "en": "Fresh seasonal fruit salad",
        "es": "Ensalada de frutas frescas de temporada",
        "ca": "Amanida de fruites fresques de temporada",
        "fr": "Salade de fruits frais de saison",
        "it": "Insalata di frutta fresca di stagione",
        "de": "Frischer Obstsalat der Saison",
        "ru": "Салат из свежих сезонных фруктов"
      },
      "description": {
        "en": "",
        "es": "",
        "ca": "",
        "fr": "",
        "it": "",
        "de": "",
        "ru": ""
      },
      "price": "7,00",
      "categoryId": "postres",
      "image": "/images/menu/frutas.jpg"
    },
    {
      "id": "chocolate",
      "name": {
        "en": "Financier chocolate crémaux and cherry coulis",
        "es": "Financier cremoso de chocolate coni coulins de  cerezas",
        "ca": "Financier cremeux de xocolata amb coulis de cireres ",
        "fr": "Financier crémeux au chocolat, cerises",
        "it": "Financier cremoso al cioccolato con ciliegie",
        "de": "Financier schokoladen-Crémeux mit Kirschen",
        "ru": "Финансист шоколадный крем с вишневым соусом"
      },
      "description": {
        "en": "",
        "es": "",
        "ca": "",
        "fr": "",
        "it": "",
        "de": "",
        "ru": ""
      },
      "price": "7,00",
      "categoryId": "postres",
      "image": "/images/menu/chocolate.jpg"
    },
    {
      "id": "helado",
      "name": {
        "en": "Selection of artisan ice creams",
        "es": "Selección de helados artesanos",
        "ca": "Selecció de gelats artesans",
        "fr": "Sélection de glaces artisanales",
        "it": "Selezione di gelati artigianali",
        "de": "Auswahl an handwerklich hergestelltem Eis",
        "ru": "Ассорти ремесленного мороженого"
      },
      "description": {
        "en": "",
        "es": "",
        "ca": "",
        "fr": "",
        "it": "",
        "de": "",
        "ru": ""
      },
      "price": "5,50",
      "categoryId": "postres",
      "image": "/images/menu/chocolate.jpg"
    }
  ]
}